nmcipher/cli/__init__.py
nmcipher/cli/detect_english.py
nmcipher/cli/parser.py
nmcipher.cli-0.0.6.dist-info/METADATA
nmcipher.cli-0.0.6.dist-info/WHEEL
nmcipher.cli-0.0.6.dist-info/entry_points.txt
nmcipher.cli-0.0.6.dist-info/top_level.txt
nmcipher.cli-0.0.6.dist-info/RECORD
